volunor/__init__.py
volunor/core/__init__.py
volunor/core/cli.py
volunor/core/command.py
volunor/core/helpers.py
volunor/test/__init__.py
volunor/test/mock.py
volunor-1.0.0rc3.dist-info/METADATA
volunor-1.0.0rc3.dist-info/WHEEL
volunor-1.0.0rc3.dist-info/LICENSE
volunor-1.0.0rc3.dist-info/RECORD
