Metadata-Version: 2.1
Name: volunor
Version: 1.0.0rc3
Summary: Command line tools, with ease
License: MIT
Author: Thomas Mahe
Author-email: contact@tmahe.dev
Requires-Python: >=3.7,<4.0
Classifier: License :: OSI Approved :: MIT License
Classifier: Programming Language :: Python :: 3
Classifier: Programming Language :: Python :: 3.7
Classifier: Programming Language :: Python :: 3.8
Classifier: Programming Language :: Python :: 3.9
Classifier: Programming Language :: Python :: 3.10
Classifier: Programming Language :: Python :: 3.11
